boto_orm/db_manager.py
boto_orm/filter.py
boto_orm/s3_manager.py
boto_orm/models/client.py
boto_orm/models/config.py
boto_orm/models/db_model.py
boto_orm-0.0.4.dist-info/METADATA
boto_orm-0.0.4.dist-info/WHEEL
boto_orm-0.0.4.dist-info/licenses/LICENSE
boto_orm-0.0.4.dist-info/RECORD
