Metadata-Version: 2.3
Name: boto-orm
Version: 0.0.4
Summary: ORM-client with connect to dynamodb-database and s3-storage.
Project-URL: Homepage, https://github.com/general-soldatov/dynamodb_manager
Project-URL: Documentation, https://github.com/general-soldatov/dynamodb_manager
Project-URL: Contacts, https://t.me/general_soldatov
Author-email: Yury Soldatov <general-soldatov@mail.ru>
License-File: LICENSE
Keywords: NoSQL,boto-client,boto3,botocore,dynamodb,s3,yandex-cloud,ydb
Classifier: License :: OSI Approved :: MIT License
Classifier: Operating System :: OS Independent
Classifier: Programming Language :: Python :: 3
Requires-Python: >=3.9
Requires-Dist: botocore<1.35.52,>=1.34.0
Requires-Dist: pydantic-settings>=2.6.0
Requires-Dist: pydantic<2.10,>=2.4.1
Requires-Dist: pyyaml>=6.0.2
Requires-Dist: typing-extensions<=5.0,>=4.7.0
